setup.py
EventManager/EventManager.py
EventManager/__init__.py
EventManager.egg-info/PKG-INFO
EventManager.egg-info/SOURCES.txt
EventManager.egg-info/dependency_links.txt
EventManager.egg-info/top_level.txt