Metadata-Version: 1.1
Name: EventManager
Version: 0.3
Summary: My take on a pythonic, and simple event system.
Home-page: https://github.com/dkkline/EventManager
Author: Jeppe Klitgaard
Author-email: jeppe@dapj.dk
License: UNKNOWN
Platform: UNKNOWN
Classifier: Development Status :: 4 - Beta
Classifier: Intended Audience :: Developers
Classifier: License :: OSI Approved :: MIT License
Classifier: Natural Language :: English
Classifier: Operating System :: OS Independent
Classifier: Programming Language :: Python
